histoclean.py
histoclean-0.0.14.dist-info/METADATA
histoclean-0.0.14.dist-info/WHEEL
histoclean-0.0.14.dist-info/top_level.txt
histoclean-0.0.14.dist-info/RECORD
